setup.py
nbcli/__init__.py
nbcli/_cli.py
notebook_cli.egg-info/PKG-INFO
notebook_cli.egg-info/SOURCES.txt
notebook_cli.egg-info/dependency_links.txt
notebook_cli.egg-info/requires.txt
notebook_cli.egg-info/top_level.txt