Metadata-Version: 1.1
Name: notebook-cli
Version: 0.1
Summary: Enables building command-line interfaces in Jupyter notebooks using IPython magics.
Home-page: https://github.com/nikhilk/nbcli
Author: Nikhil Kothari
Author-email: UNKNOWN
License: BSD
Keywords: cli commandline jupyter interactive argparse yaml ipython
Platform: UNKNOWN
Classifier: Development Status :: 3 - Alpha
Classifier: Framework :: IPython
Classifier: Framework :: Jupyter
Classifier: Programming Language :: Python
Classifier: Programming Language :: Python :: 2.7
Classifier: License :: OSI Approved :: Apache Software License
